wagtail_cloudinary_image/__init__.py
wagtail_cloudinary_image/abstract.py
wagtail_cloudinary_image/admin.py
wagtail_cloudinary_image/apps.py
wagtail_cloudinary_image/migrations/0001_initial.py
wagtail_cloudinary_image/migrations/__init__.py
wagtail_cloudinary_image/models.py
wagtail_cloudinary_image/tests.py
wagtail_cloudinary_image/views.py
wagtail_cloudinary_image-0.0.3.dist-info/LICENSE
wagtail_cloudinary_image-0.0.3.dist-info/WHEEL
wagtail_cloudinary_image-0.0.3.dist-info/METADATA
wagtail_cloudinary_image-0.0.3.dist-info/RECORD
