Metadata-Version: 2.1
Name: wagtail-cloudinary-image
Version: 0.0.3
Summary: Wagtail Image model that utilized django-cloudinary-storage
Author: David Burke
Author-email: david@burkesoftware.com
Requires-Python: >=3.7,<4.0
Classifier: Development Status :: 5 - Production/Stable
Classifier: Environment :: Web Environment
Classifier: Framework :: Django
Classifier: Framework :: Wagtail
Classifier: Intended Audience :: Developers
Classifier: License :: OSI Approved :: Apache Software License
Classifier: Programming Language :: Python
Classifier: Programming Language :: Python :: 3
Classifier: Programming Language :: Python :: 3.7
Classifier: Programming Language :: Python :: 3.8
Requires-Dist: Django (>=2.2)
Requires-Dist: cloudinary (>=1.22.0)
Requires-Dist: django-cloudinary-storage (>=0.3.0)
Requires-Dist: wagtail (>=2.9)
